division_multiplication/__init__.py
division_multiplication/divi.py
division_multiplication/multi.py
division_multiplication-0.5.dist-info/METADATA
division_multiplication-0.5.dist-info/WHEEL
division_multiplication-0.5.dist-info/top_level.txt
division_multiplication-0.5.dist-info/RECORD
