Metadata-Version: 2.1
Name: division-multiplication
Version: 0.5
Summary: Division and Multiplication by three updated
Home-page: UNKNOWN
Author: Love Kadiya
Author-email: love.kadiya@acquaintsoft.com
License: UNKNOWN
Platform: UNKNOWN
